ChemDoE/__init__.py
ChemDoE/analyses_uploader.py
ChemDoE/cli.py
ChemDoE/config.py
ChemDoE/doe_manager.py
ChemDoE/element_tree_page.py
ChemDoE/examples/csv_sample.csv
ChemDoE/examples/csv_sample.py
ChemDoE/examples/json_sample.R
ChemDoE/examples/json_sample.json
ChemDoE/examples/json_sample.py
ChemDoE/examples/out_csv_sample.csv
ChemDoE/examples/out_json_sample.json
ChemDoE/execute.py
ChemDoE/icons/__init__.py
ChemDoE/icons/downloader.py
ChemDoE/icons/fixed/R.png
ChemDoE/icons/fixed/arrow-left-circle-fill.svg.png
ChemDoE/icons/fixed/arrow-right-circle-fill.svg.png
ChemDoE/icons/fixed/chemotion-full.ico
ChemDoE/icons/fixed/chemotion-full.png
ChemDoE/icons/fixed/fav.png
ChemDoE/icons/fixed/flask.svg.png
ChemDoE/icons/fixed/folder.svg.png
ChemDoE/icons/fixed/info.png
ChemDoE/icons/fixed/loading.gif
ChemDoE/icons/fixed/no_fav.png
ChemDoE/icons/fixed/plus.svg.png
ChemDoE/icons/fixed/python.png
ChemDoE/icons/fixed/sample.png
ChemDoE/icons/fixed/search.png
ChemDoE/icons/fixed/trash.png
ChemDoE/login_manager.py
ChemDoE/main.py
ChemDoE/new_reaction.py
ChemDoE/new_sample.py
ChemDoE/registration/__init__.py
ChemDoE/registration/loader.py
ChemDoE/registration/result_validater.py
ChemDoE/script_manager.py
ChemDoE/start.md
ChemDoE/start_view.py
ChemDoE/test.json
ChemDoE/utils/MdField.py
ChemDoE/utils/__init__.py
ChemDoE/utils/dd_manager.py
ChemDoE/utils/keyboard_shortcuts.py
ChemDoE/utils/page_manager.py
ChemDoE/utils/pages.py
ChemDoE/utils/utils.py
chemdoe-0.2.1.dist-info/LICENSE
chemdoe-0.2.1.dist-info/METADATA
chemdoe-0.2.1.dist-info/WHEEL
chemdoe-0.2.1.dist-info/entry_points.txt
chemdoe-0.2.1.dist-info/RECORD
