Metadata-Version: 2.3
Name: chemdoe
Version: 0.2.1
Summary: 
Author: Martin Starman
Author-email: martin.starman@kit.edu
Requires-Python: >=3.11,<3.14
Classifier: Programming Language :: Python :: 3
Classifier: Programming Language :: Python :: 3.11
Classifier: Programming Language :: Python :: 3.12
Classifier: Programming Language :: Python :: 3.13
Requires-Dist: beautifulsoup4 (>=4.13.3,<5.0.0)
Requires-Dist: cairosvg (>=2.7.1,<3.0.0)
Requires-Dist: chemotion-api (==0.4.3)
Requires-Dist: click (>=8.1.8,<9.0.0)
Requires-Dist: pillow (>=11.1.0,<12.0.0)
Requires-Dist: platformdirs (>=4.3.6,<5.0.0)
Requires-Dist: pyinstaller (>=6.12.0,<7.0.0)
Requires-Dist: pytest (>=8.3.5,<9.0.0)
Requires-Dist: python-magic-bin (>=0.4.14,<0.5.0) ; sys_platform == "win32"
Requires-Dist: requests (>=2.32.3,<3.0.0)
Requires-Dist: tk (>=0.1.0,<0.2.0)
